lmdirect/__init__.py
lmdirect/aescipher.py
lmdirect/cmds.py
lmdirect/connection.py
lmdirect/const.py
lmdirect/msgs.py
lmdirect-0.9.4.dist-info/LICENSE
lmdirect-0.9.4.dist-info/METADATA
lmdirect-0.9.4.dist-info/WHEEL
lmdirect-0.9.4.dist-info/top_level.txt
lmdirect-0.9.4.dist-info/RECORD
