Metadata-Version: 2.1
Name: lmdirect
Version: 0.9.4
Summary: A Python implementation of the local La Marzocco API
Home-page: https://github.com/rccoleman/lmdirect
Author: Rob Coleman
Author-email: rccoleman@gmail.com
License: MIT
Platform: UNKNOWN
Classifier: Development Status :: 3 - Alpha
Classifier: Intended Audience :: Developers
Classifier: Natural Language :: English
Classifier: License :: OSI Approved :: MIT License
Classifier: Programming Language :: Python
Classifier: Programming Language :: Python :: 3.8
Classifier: Programming Language :: Python :: Implementation :: CPython
Requires-Dist: pycryptodome (>=3.9.9)
Requires-Dist: httpx (>=0.16.1)
Requires-Dist: authlib (<1.*,>=0.15.5)
